debug_toolbar_user_switcher/__init__.py
debug_toolbar_user_switcher/decorators.py
debug_toolbar_user_switcher/forms.py
debug_toolbar_user_switcher/panels.py
debug_toolbar_user_switcher/templates/debug_toolbar_user_switcher/panel.html
debug_toolbar_user_switcher/views.py
django_debug_toolbar_user_switcher-2.2.0.dist-info/COPYING
django_debug_toolbar_user_switcher-2.2.0.dist-info/WHEEL
django_debug_toolbar_user_switcher-2.2.0.dist-info/METADATA
django_debug_toolbar_user_switcher-2.2.0.dist-info/RECORD
